Workbook

Sheet Dashboard
A1: CLÍNICA PERSONART - CONTROLE FINANCEIRO 2026
A3: Resumo Executivo - Balanço Mensal
A4: MÊS | B4: RECEITAS | C4: DESPESAS | D4: IMPOSTOS | E4: RESULTADO LÍQUIDO | F4: MARGEM (%)
A5: JANEIRO | B5: ='Resumo Mensal'!B4 -> 440 | C5: ='Resumo Mensal'!C4 -> 590 | D5: ='Resumo Mensal'!D4 -> 0 | E5: ='Resumo Mensal'!E4 -> 0 | F5: ='Resumo Mensal'!F4 -> 0 | G5: ='Resumo Mensal'!G4 -> 0 | H5: ='Resumo Mensal'!H4 -> 0 | I5: ='Resumo Mensal'!I4 -> 0 | ... M5: ='Resumo Mensal'!M4 -> 1030
A6: FEVEREIRO | B6: ='Resumo Mensal'!B5 | C6: ='Resumo Mensal'!C5 | D6: ='Resumo Mensal'!D5 | E6: ='Resumo Mensal'!E5 | F6: ='Resumo Mensal'!F5 | G6: ='Resumo Mensal'!G5 | H6: ='Resumo Mensal'!H5 | I6: ='Resumo Mensal'!I5 | ... M6: ='Resumo Mensal'!M5 -> 0
A7: MARÇO | B7: ='Resumo Mensal'!B6 -> 720.55 | C7: ='Resumo Mensal'!C6 -> 0 | D7: ='Resumo Mensal'!D6 -> 0 | E7: ='Resumo Mensal'!E6 -> 0 | F7: ='Resumo Mensal'!F6 -> 0 | G7: ='Resumo Mensal'!G6 -> 0 | H7: ='Resumo Mensal'!H6 -> 0 | I7: ='Resumo Mensal'!I6 -> 0 | ... M7: ='Resumo Mensal'!M6 -> 720.55
A8: ABRIL | B8: =B5-B6-B7 -> -280.55 | C8: =C5-C6-C7 -> 590 | D8: =D5-D6-D7 -> 0 | E8: =E5-E6-E7 -> 0 | F8: =F5-F6-F7 -> 0 | G8: =G5-G6-G7 -> 0 | H8: =H5-H6-H7 -> 0 | I8: =I5-I6-I7 -> 0 | ... M8: =M5-M6-M7 -> 309.45
A9: MAIO | B9: =IF(B5=0,0,(B8/B5)*100) -> -63.761364 | C9: =IF(C5=0,0,(C8/C5)*100) -> 100 | D9: =IF(D5=0,0,(D8/D5)*100) -> 0 | E9: =IF(E5=0,0,(E8/E5)*100) -> 0 | F9: =IF(F5=0,0,(F8/F5)*100) -> 0 | G9: =IF(G5=0,0,(G8/G5)*100) -> 0 | H9: =IF(H5=0,0,(H8/H5)*100) -> 0 | I9: =IF(I5=0,0,(I8/I5)*100) -> 0 | ... M9: =IF(M5=0,0,(M8/M5)*100) -> 30.043689
A10: JUNHO
A11: JULHO
A12: AGOSTO
A13: SETEMBRO
A14: OUTUBRO
A15: NOVEMBRO
A16: DEZEMBRO
A17: TOTAL ANUAL | B17: =SUM(B5:B9) -> 816.23864 | C17: =SUM(C5:C9) -> 1280 | D17: =SUM(D5:D9) -> 0 | E17: =SUM(E5:E9) -> 0 | F17: =SUM(F5:F9) -> 0 | G17: =SUM(G5:G9) -> 0 | H17: =SUM(H5:H9) -> 0 | I17: =SUM(I5:I9) -> 0 | ... M17: =SUM(M5:M9) -> 2090.0437

Sheet Receitas
A1: RECEITAS - 2026
A3: DESCRIÇÃO | B3: JANEIRO | C3: FEVEREIRO | D3: MARÇO | E3: ABRIL | F3: MAIO | G3: JUNHO | H3: JULHO | I3: AGOSTO | J3: SETEMBRO | K3: OUTUBRO | L3: NOVEMBRO | M3: DEZEMBRO | N3: TOTAL
A5: Aluguel - Simone | B5: 220 | C5: 220
A6: Aluguel - Adriele | B6: 110 | C6: 110
A7: Aluguel - Giovana | C7: 150
A8: Aluguel - Geovanna | B8: 110 | C8: 110
A9: Funserv | B9: 7880.36
A10: Fussex
A11: Danamed | B11: 960
A12: Gama
A13: Bruno | B13: 855
A14: Janaina | B14: 800
A15: Soraia | B15: 530
A16: Stephanie | B16: 884
A17: TOTAL DE RECEITAS | B17: =SUM(B4:B8) -> 440 | C17: =SUM(C4:C8) -> 590 | D17: =SUM(D4:D8) -> 0 | E17: =SUM(E4:E8) -> 0 | F17: =SUM(F4:F8) -> 0 | G17: =SUM(G4:G8) -> 0 | H17: =SUM(H4:H8) -> 0 | I17: =SUM(I4:I8) -> 0 | ... L17: =SUM(L4:L8) -> 0 | M17: =SUM(B17:L17) -> 1030

Sheet Despesas
A1: DESPESAS - 2026
A3: DESCRIÇÃO | B3: JANEIRO | C3: FEVEREIRO | D3: MARÇO | E3: ABRIL | F3: MAIO | G3: JUNHO | H3: JULHO | I3: AGOSTO | J3: SETEMBRO | K3: OUTUBRO | L3: NOVEMBRO | M3: DEZEMBRO | N3: TOTAL
A4: DESPESAS FIXAS
A5: Aluguel | B5: 1600 | C5: 1600 | D5: 1600 | E5: 1600 | F5: 1600 | G5: 1600 | H5: 1600 | I5: 1600 | J5: 1600 | K5: 1600 | L5: 1600 | M5: 1600
A6: Agua ( SAAE) | B6: 79.39
A7: Energia ( CPFL) | B7: 436.74
A8: Internet | B8: 221.98 | C8: 111 | D8: 111 | E8: 111 | F8: 111 | G8: 111 | H8: 111 | I8: 111 | J8: 111 | K8: 111 | L8: 111 | M8: 111
A9: Contabilidade | B9: 350 | C9: 350 | D9: 350 | E9: 350 | F9: 350 | G9: 350 | H9: 350 | I9: 350 | J9: 350 | K9: 350 | L9: 350 | M9: 350
A10: Ar Condicionado/Climatização | B10: 529.42 | C10: 549.42 | D10: 549.42
A11: CRP jurídico | B11: 159.79 | C11: 159.79 | D11: 159.79 | E11: 159.79 | F11: 159.79 | G11: 159.79
A12: Certificado Digital | E12: 150 | F12: 150 | G12: 150
A13: Impressora | C13: 149.67 | D13: 149.67 | E13: 149.67 | F13: 149.67 | G13: 149.67 | H13: 149.67
A14: Compra insumos p/ clinica | B14: 300
A15: Propaganda / Marketing | B15: 50
A16: Caixa para Manutenção/ Clinica | B16: 50
A19: SUBTOTAL FIXAS | B19: =SUM(B5:B13) -> 3377.32 | C19: =SUM(C5:C13) -> 2919.88 | D19: =SUM(D5:D12) -> 2770.21 | E19: =SUM(E5:E12) -> 2370.79 | F19: =SUM(F5:F12) -> 2370.79 | G19: =SUM(G5:G12) -> 2370.79 | H19: =SUM(H5:H12) -> 2061 | I19: =SUM(I5:I12) -> 2061 | J19: =SUM(J5:J12) -> 2061 | K19: =SUM(K5:K12) -> 2061 | ... M19: =SUM(M5:M12) -> 2061
A21: DESPESAS VARIÁVEIS
A22: Ar condicionado | B22: 529.42 | C22: 549.42 | D22: 549.42
A23: Instalação do Ar
A24: Compra Impressora | C24: 149.67 | D24: 149.67 | E24: 149.67 | F24: 149.67 | G24: 149.67 | H24: 149.67
A25: Certificado Digital | E25: 150 | F25: 150 | G25: 150
A26: CRP / Clinica | B26: 159.79 | C26: 159.79 | D26: 159.79 | E26: 159.79 | F26: 159.79 | G26: 159.79
M27: =SUM(B27:L27) -> 0
A29: Limpeza do jardim | B29: 70
A30: SUBTOTAL VARIÁVEIS | B30: =SUM(B22:B29) -> 759.21 | C30: =SUM(C22:C29) -> 858.88 | D30: =SUM(D22:D29) -> 858.88 | E30: =SUM(E22:E29) -> 459.46 | F30: =SUM(F22:F29) -> 459.46 | G30: =SUM(G22:G29) -> 459.46 | H30: =SUM(H22:H29) -> 149.67 | I30: =SUM(I22:I29) -> 0 | ... M30: =SUM(M22:M29) -> 0
A31: TOTAL DE DESPESAS | B31: =B19+B30 -> 4136.53 | C31: =C19+C30 -> 3778.76 | D31: =D19+D30 -> 3629.09 | E31: =E19+E30 -> 2830.25 | F31: =F19+F30 -> 2830.25 | G31: =G19+G30 -> 2830.25 | H31: =H19+H30 -> 2210.67 | I31: =I19+I30 -> 2061 | ... M31: =M19+M30 -> 2061

Sheet Impostos
A1: IMPOSTOS E CONTRIBUIÇÕES - 2026
A3: DESCRIÇÃO | B3: JANEIRO | C3: FEVEREIRO | D3: MARÇO | E3: ABRIL | F3: MAIO | G3: JUNHO | H3: JULHO | I3: AGOSTO | J3: SETEMBRO | K3: OUTUBRO | L3: NOVEMBRO | M3: DEZEMBRO | N3: TOTAL
A4: ISS (Imposto Sobre Serviços)
A5: DAS (Microempreendedor) | B5: 415.76
A6: DARF (Imposto de Renda) | B6: 304.79
A7: IRPJ (Imposto de Renda PJ)
A8: CSLL (Contribuição Social)
A9: TOTAL DE IMPOSTOS | B9: =SUM(B4:B8) -> 720.55 | C9: =SUM(C4:C8) -> 0 | D9: =SUM(D4:D8) -> 0 | E9: =SUM(E4:E8) -> 0 | F9: =SUM(F4:F8) -> 0 | G9: =SUM(G4:G8) -> 0 | H9: =SUM(H4:H8) -> 0 | I9: =SUM(I4:I8) -> 0 | ... L9: =SUM(L4:L8) -> 0 | M9: =SUM(B9:L9) -> 720.55

Sheet Profissionais
A1: PAGAMENTOS A PROFISSIONAIS E ALUGUEL - 2026
A3: PROFISSIONAL / DESCRIÇÃO | B3: JANEIRO | C3: FEVEREIRO | D3: MARÇO | E3: ABRIL | F3: MAIO | G3: JUNHO | H3: JULHO | I3: AGOSTO | J3: SETEMBRO | K3: OUTUBRO | L3: NOVEMBRO | M3: DEZEMBRO | N3: TOTAL
A4: Simone - | B4: 1293.47
A5: Adriele - | B5: 922
A6: Geovanna | B6: 1107
A7: Giovana
A8: Bruno | B8: 1816
A9: Stephanie | B9: 2878.64
A10: Janaina | B10: 1682.4
A11: Maria | B11: 144
A12: Soraia | B12: 883.2
A16: TOTAL DE PAGAMENTOS | B16: =SUM(B4:B12) -> 10726.71 | C16: =SUM(C4:C12) -> 0 | D16: =SUM(D4:D12) -> 0 | E16: =SUM(E4:E12) -> 0 | F16: =SUM(F4:F12) -> 0 | G16: =SUM(G4:G12) -> 0 | H16: =SUM(H4:H12) -> 0 | I16: =SUM(I4:I12) -> 0 | ... L16: =SUM(L4:L12) -> 0 | M16: =SUM(B16:L16) -> 10726.71
A18: Previsão de pagamento
A19: Simone -
A20: Adriele - | B20: 922
A21: Geovanna
A22: Giovana
A23: Bruno
A24: Stephanie
A25: Janaina
A26: Maria
A27: Soraia

Sheet Resumo Mensal
A1: BALANÇO MENSAL - 2026
A3: DESCRIÇÃO | B3: JANEIRO | C3: FEVEREIRO | D3: MARÇO | E3: ABRIL | F3: MAIO | G3: JUNHO | H3: JULHO | I3: AGOSTO | J3: SETEMBRO | K3: OUTUBRO | L3: NOVEMBRO | M3: DEZEMBRO | N3: TOTAL
A4: RECEITAS TOTAIS | B4: =Receitas!B17 -> 440 | C4: =Receitas!C17 -> 590 | D4: =Receitas!D17 -> 0 | E4: =Receitas!E17 -> 0 | F4: =Receitas!F17 -> 0 | G4: =Receitas!G17 -> 0 | H4: =Receitas!H17 -> 0 | I4: =Receitas!I17 -> 0 | ... L4: =Receitas!L17 -> 0 | M4: =SUM(B4:L4) -> 1030
A5: DESPESAS TOTAIS | B5: =Despesas!B27 | C5: =Despesas!C27 | D5: =Despesas!D27 | E5: =Despesas!E27 | F5: =Despesas!F27 | G5: =Despesas!G27 | H5: =Despesas!H27 | I5: =Despesas!I27 | ... L5: =Despesas!L27 | M5: =SUM(B5:L5) -> 0
A6: IMPOSTOS TOTAIS | B6: =Impostos!B9 -> 720.55 | C6: =Impostos!C9 -> 0 | D6: =Impostos!D9 -> 0 | E6: =Impostos!E9 -> 0 | F6: =Impostos!F9 -> 0 | G6: =Impostos!G9 -> 0 | H6: =Impostos!H9 -> 0 | I6: =Impostos!I9 -> 0 | ... L6: =Impostos!L9 -> 0 | M6: =SUM(B6:L6) -> 720.55
A7: PAGAMENTOS A PROFISSIONAIS | B7: =Profissionais!B16 -> 10726.71 | C7: =Profissionais!C16 -> 0 | D7: =Profissionais!D16 -> 0 | E7: =Profissionais!E16 -> 0 | F7: =Profissionais!F16 -> 0 | G7: =Profissionais!G16 -> 0 | H7: =Profissionais!H16 -> 0 | I7: =Profissionais!I16 -> 0 | ... L7: =Profissionais!L16 -> 0 | M7: =SUM(B7:L7) -> 10726.71
A9: RESULTADO LÍQUIDO | B9: =B4-B5-B6-B7 -> -11007.26 | C9: =C4-C5-C6-C7 -> 590 | D9: =D4-D5-D6-D7 -> 0 | E9: =E4-E5-E6-E7 -> 0 | F9: =F4-F5-F6-F7 -> 0 | G9: =G4-G5-G6-G7 -> 0 | H9: =H4-H5-H6-H7 -> 0 | I9: =I4-I5-I6-I7 -> 0 | ... L9: =L4-L5-L6-L7 -> 0 | M9: =SUM(B9:L9) -> -10417.26
A10: MARGEM DE LUCRO (%) | B10: =IF(B4=0,0,(B9/B4)*100) -> -2501.65 | C10: =IF(C4=0,0,(C9/C4)*100) -> 100 | D10: =IF(D4=0,0,(D9/D4)*100) -> 0 | E10: =IF(E4=0,0,(E9/E4)*100) -> 0 | F10: =IF(F4=0,0,(F9/F4)*100) -> 0 | G10: =IF(G4=0,0,(G9/G4)*100) -> 0 | H10: =IF(H4=0,0,(H9/H4)*100) -> 0 | I10: =IF(I4=0,0,(I9/I4)*100) -> 0 | ... M10: =IF(M4=0,0,(M9/M4)*100) -> -1011.3845
